delocalizer/__init__.py
delocalizer/delocalizer.py
delocalizer/extractor.py
delocalizer/honorific.py
delocalizer/main.py
delocalizer/md_subs.py
delocalizer/utils/lambda_fetch.py
delocalizer-0.5.dist-info/LICENSE
delocalizer-0.5.dist-info/METADATA
delocalizer-0.5.dist-info/WHEEL
delocalizer-0.5.dist-info/entry_points.txt
delocalizer-0.5.dist-info/RECORD
