Metadata-Version: 2.1
Name: delocalizer
Version: 0.5
Summary: 
Author: Efrain
Author-email: efrondx@gmail.com
Requires-Python: >=3.8,<4.0
Classifier: Programming Language :: Python :: 3
Classifier: Programming Language :: Python :: 3.8
Classifier: Programming Language :: Python :: 3.9
Classifier: Programming Language :: Python :: 3.10
Classifier: Programming Language :: Python :: 3.11
Classifier: Programming Language :: Python :: 3.12
Requires-Dist: modify-subs (>=0.5.1,<0.6.0)
Requires-Dist: pysubs2 (>=1.7.3,<2.0.0)
Requires-Dist: python-dotenv (>=1.0.1,<2.0.0)
Requires-Dist: requests (>=2.32.3,<3.0.0)
Requires-Dist: subdeloc-tools (>=0.9.11,<0.10.0)
